django_popup_field-0.1.6.dist-info/METADATA
django_popup_field-0.1.6.dist-info/RECORD
django_popup_field-0.1.6.dist-info/WHEEL
django_popup_field-0.1.6.dist-info/top_level.txt
popup_field/__init__.py
popup_field/fields.py
popup_field/tests.py
popup_field/views.py
popup_field/static/jquery/jquery-2.1.3.min.js
popup_field/static/jquery/jquery.cookie.js
popup_field/static/layer/layer.js
popup_field/static/layer/mobile/layer.js
popup_field/static/layer/mobile/need/layer.css
popup_field/static/layer/theme/default/icon-ext.png
popup_field/static/layer/theme/default/icon.png
popup_field/static/layer/theme/default/layer.css
popup_field/static/layer/theme/default/loading-0.gif
popup_field/static/layer/theme/default/loading-1.gif
popup_field/static/layer/theme/default/loading-2.gif
popup_field/static/popup_crud/button.css
popup_field/static/popup_field/button.css
popup_field/templates/popup/base.html
popup_field/templates/popup/success.html
popup_field/templates/widgets/foreign_key_select.html
popup_field/templates/widgets/many_to_many_select.html
