Metadata-Version: 2.1
Name: django-popup-field
Version: 0.1.6
Summary: A popup field for django which can create\update\delete ForeignKey and ManyToManyField instance by popup windows.
Home-page: https://github.com/yinkh/django-popup-field.git
Author: Yin KangHong
Author-email: 614457662@qq.com
License: BSD 3-Clause License
Keywords: django-popup-field
Platform: UNKNOWN
Classifier: Development Status :: 3 - Alpha
Classifier: Intended Audience :: Developers
Classifier: License :: OSI Approved :: MIT License
Classifier: Operating System :: OS Independent
Classifier: Programming Language :: Python :: 3
Classifier: Topic :: Software Development :: Libraries
Classifier: Environment :: Web Environment
Classifier: Framework :: Django
